Metadata-Version: 2.4
Name: JSON2CSVLIB
Version: 1.0.0
Summary: A professional JSON to CSV conversion library
Home-page: https://github.com/yourusername/json2csv-pro
Author: Manu c
Author-email: Manu C <manuachu0611@gmail.com>
License: MIT
Project-URL: Homepage, https://github.com/yourusername/json2csv-pro
Project-URL: Documentation, https://json2csv-pro.readthedocs.io
Project-URL: Repository, https://github.com/yourusername/json2csv-pro
Project-URL: Bug Tracker, https://github.com/yourusername/json2csv-pro/issues
Keywords: json,csv,converter,data,conversion
Classifier: Development Status :: 5 - Production/Stable
Classifier: Intended Audience :: Developers
Classifier: License :: OSI Approved :: MIT License
Classifier: Programming Language :: Python :: 3
Classifier: Programming Language :: Python :: 3.8
Classifier: Programming Language :: Python :: 3.9
Classifier: Programming Language :: Python :: 3.10
Classifier: Programming Language :: Python :: 3.11
Classifier: Programming Language :: Python :: 3.12
Requires-Python: >=3.8
License-File: LICENSE
Dynamic: author
Dynamic: home-page
Dynamic: license-file
Dynamic: requires-python
